PyGWAS-1.7.4.dist-info/METADATA
PyGWAS-1.7.4.dist-info/RECORD
PyGWAS-1.7.4.dist-info/WHEEL
PyGWAS-1.7.4.dist-info/entry_points.txt
PyGWAS-1.7.4.dist-info/pbr.json
PyGWAS-1.7.4.dist-info/top_level.txt
pygwas/__init__.py
pygwas/__main__.py
pygwas/plotter.py
pygwas/pygwas.py
pygwas/samples.py
pygwas/core/__init__.py
pygwas/core/data_parsers.py
pygwas/core/enrichment.py
pygwas/core/genotype.py
pygwas/core/gwas.py
pygwas/core/kinship.py
pygwas/core/ld.py
pygwas/core/linear_models.py
pygwas/core/mtcorr.py
pygwas/core/phenotype.py
pygwas/core/phenotypes.py
pygwas/core/plot.py
pygwas/core/plotting.py
pygwas/core/result.py
pygwas/core/statistics.py
pygwas/core/timer.py
